astbuilder/__init__.py
astbuilder/__main__.py
astbuilder/ast.py
astbuilder/ast_class.py
astbuilder/ast_data.py
astbuilder/ast_enum.py
astbuilder/ast_flags.py
astbuilder/ast_ref.py
astbuilder/ast_struct.py
astbuilder/cpp_accessor_gen.py
astbuilder/cpp_gen_factory.py
astbuilder/cpp_gen_fwd_decl.py
astbuilder/cpp_gen_ns.py
astbuilder/cpp_gen_params.py
astbuilder/cpp_type_name_gen.py
astbuilder/gen_cpp.py
astbuilder/gen_cpp_visitor.py
astbuilder/linker.py
astbuilder/outstream.py
astbuilder/parser.py
astbuilder/pyext_accessor_gen.py
astbuilder/pyext_gen.py
astbuilder/pyext_gen_extdef.py
astbuilder/pyext_gen_factory.py
astbuilder/pyext_gen_params.py
astbuilder/pyext_gen_ptrdefs.py
astbuilder/pyext_gen_pyx.py
astbuilder/pyext_gen_visitor.py
astbuilder/pyext_list_accessor_gen.py
astbuilder/pyext_type_name_gen.py
astbuilder/type_list.py
astbuilder/type_map.py
astbuilder/type_pointer.py
astbuilder/type_scalar.py
astbuilder/type_userdef.py
astbuilder/visitor.py
astbuilder/cmds/__init__.py
astbuilder/cmds/gen_cpp.py
astbuilder/cmds/gen_pyext.py
astbuilder/cmds/util.py
pyastbuilder-0.0.2.9408869921.dist-info/LICENSE
pyastbuilder-0.0.2.9408869921.dist-info/METADATA
pyastbuilder-0.0.2.9408869921.dist-info/WHEEL
pyastbuilder-0.0.2.9408869921.dist-info/entry_points.txt
pyastbuilder-0.0.2.9408869921.dist-info/top_level.txt
pyastbuilder-0.0.2.9408869921.dist-info/RECORD
