Metadata-Version: 2.1
Name: pyastbuilder
Version: 0.0.2.9408869921
Summary: Utility for generating AST classes from a yaml description
Home-page: https://github.com/mballance/pyastbuilder
Author: Matthew Ballance
Author-email: matt.ballance@gmail.com
License: Apache 2.0
Keywords: Parsing
License-File: LICENSE
Requires-Dist: pyyaml
Requires-Dist: toposort
